python_ollama/__init__.py
python_ollama/api.py
python_ollama/parameters.py
Python_Ollama-0.2.4.dist-info/LICENSE
Python_Ollama-0.2.4.dist-info/METADATA
Python_Ollama-0.2.4.dist-info/WHEEL
Python_Ollama-0.2.4.dist-info/top_level.txt
Python_Ollama-0.2.4.dist-info/RECORD
