Metadata-Version: 2.1
Name: Python-Ollama
Version: 0.2.4
Summary: Python client for the Ollama API
Home-page: https://github.com/DarsheeeGamer/Python-Ollama/
Author: Kaede Dev Kento Hinode
Author-email: cleaverdeath@gmail.com
Classifier: Programming Language :: Python :: 3
Classifier: License :: OSI Approved :: MIT License
Classifier: Operating System :: OS Independent
License-File: LICENSE
Requires-Dist: requests
